bonfire/Bot.py
bonfire/__init__.py
bonfire/methods.py
bonfire/method/__init__.py
bonfire/method/button.py
bonfire/method/delete.py
bonfire/method/edit.py
bonfire/method/photo.py
bonfire/method/reply.py
bonfire/method/send.py
bonfire/method/sticker.py
bonfire_tg-1.1.1.dist-info/LICENSE
bonfire_tg-1.1.1.dist-info/METADATA
bonfire_tg-1.1.1.dist-info/WHEEL
bonfire_tg-1.1.1.dist-info/top_level.txt
bonfire_tg-1.1.1.dist-info/RECORD
