Metadata-Version: 2.1
Name: bonfire-tg
Version: 1.1.1
Summary: telegram api libraly
Home-page: https://github.com/Help-urself/bonfire
Author: Help_urself
Author-email: alexliulev1@gmail.com
License: UNKNOWN
Platform: UNKNOWN
Classifier: Programming Language :: Python :: 3.7
Classifier: Programming Language :: Python :: 3.8
Classifier: Programming Language :: Python :: 3.9
Classifier: Programming Language :: Python :: 3.10
Classifier: License :: OSI Approved :: MIT License
Classifier: Operating System :: OS Independent
Requires-Python: >=3.7
License-File: LICENSE
Requires-Dist: requests (>=2.27.1)
Requires-Dist: colorama (>=0.4.6)
Requires-Dist: APScheduler (>=3.9.1.post1)
